switchbotble/__init__.py
switchbotble/base.py
switchbotble/devices/__init__.py
switchbotble/devices/base.py
switchbotble/devices/contact_sensor.py
switchbotble/devices/factory.py
switchbotble/devices/meter.py
switchbotble/devices/meter_pro.py
switchbotble/devices/motion_sensor.py
switchbotble/devices/unknown_sensor.py
switchbotble/devices/water_leak_detector.py
switchbotble-0.3.0.dist-info/LICENSE
switchbotble-0.3.0.dist-info/METADATA
switchbotble-0.3.0.dist-info/WHEEL
switchbotble-0.3.0.dist-info/top_level.txt
switchbotble-0.3.0.dist-info/RECORD
